package/__init__.py
package/main.py
howtocheckexi-1.0.0.dist-info/LICENCE
howtocheckexi-1.0.0.dist-info/METADATA
howtocheckexi-1.0.0.dist-info/WHEEL
howtocheckexi-1.0.0.dist-info/top_level.txt
howtocheckexi-1.0.0.dist-info/RECORD
