Metadata-Version: 2.1
Name: howtocheckexi
Version: 1.0.0
Summary: This is my first module
Home-page: https://github.com/SocratDel/howtocheckexi
Author: your_nickname
Author-email: example@gmail.com
Project-URL: Documentation, https://github.com/SocratDel/howtocheckexi
Keywords: example python
Classifier: Programming Language :: Python :: 3.11
Classifier: License :: OSI Approved :: MIT License
Classifier: Operating System :: OS Independent
Requires-Python: >=3.7
License-File: LICENCE
Requires-Dist: requests (>=2.25.1)
